LICENSE
MANIFEST.in
README.rst
setup.cfg
setup.py
pytest_random_num.egg-info/PKG-INFO
pytest_random_num.egg-info/SOURCES.txt
pytest_random_num.egg-info/dependency_links.txt
pytest_random_num.egg-info/entry_points.txt
pytest_random_num.egg-info/requires.txt
pytest_random_num.egg-info/top_level.txt
random_order/__init__.py
random_order/bucket_types.py
random_order/cache.py
random_order/config.py
random_order/plugin.py
random_order/shuffler.py
tests/__init__.py
tests/conftest.py
tests/test_actual_test_runs.py
tests/test_cli.py
tests/test_demo.py
tests/test_doctests.py
tests/test_markers.py
tests/test_plugin_failure.py
tests/test_shuffle.py